odoo/addons/account_purchase_stock_report_non_billed/README.rst
odoo/addons/account_purchase_stock_report_non_billed/__init__.py
odoo/addons/account_purchase_stock_report_non_billed/__manifest__.py
odoo/addons/account_purchase_stock_report_non_billed/i18n/account_purchase_stock_report_non_billed.pot
odoo/addons/account_purchase_stock_report_non_billed/i18n/es.po
odoo/addons/account_purchase_stock_report_non_billed/i18n/it.po
odoo/addons/account_purchase_stock_report_non_billed/i18n/pt_BR.po
odoo/addons/account_purchase_stock_report_non_billed/models/__init__.py
odoo/addons/account_purchase_stock_report_non_billed/models/stock_move.py
odoo/addons/account_purchase_stock_report_non_billed/readme/CONTRIBUTORS.md
odoo/addons/account_purchase_stock_report_non_billed/readme/DESCRIPTION.md
odoo/addons/account_purchase_stock_report_non_billed/readme/USAGE.md
odoo/addons/account_purchase_stock_report_non_billed/static/description/icon.png
odoo/addons/account_purchase_stock_report_non_billed/static/description/index.html
odoo/addons/account_purchase_stock_report_non_billed/tests/__init__.py
odoo/addons/account_purchase_stock_report_non_billed/tests/test_account_purchase_stock_report_non_billed.py
odoo/addons/account_purchase_stock_report_non_billed/wizard/__init__.py
odoo/addons/account_purchase_stock_report_non_billed/wizard/account_sale_stock_report_non_billed_wiz.py
odoo_addon_account_purchase_stock_report_non_billed-17.0.1.0.0.2.dist-info/METADATA
odoo_addon_account_purchase_stock_report_non_billed-17.0.1.0.0.2.dist-info/WHEEL
odoo_addon_account_purchase_stock_report_non_billed-17.0.1.0.0.2.dist-info/top_level.txt
odoo_addon_account_purchase_stock_report_non_billed-17.0.1.0.0.2.dist-info/RECORD
