Metadata-Version: 2.1
Name: odoo-addon-account_purchase_stock_report_non_billed
Version: 17.0.1.0.0.2
Requires-Python: >=3.10
Requires-Dist: odoo-addon-account_sale_stock_report_non_billed>=17.0dev,<17.1dev
Requires-Dist: odoo-addon-purchase_stock_picking_invoice_link>=17.0dev,<17.1dev
Requires-Dist: odoo>=17.0a,<17.1dev
Summary: Account Purchase Stock Report Non Billed
Home-page: https://github.com/OCA/account-financial-reporting
License: AGPL-3
Author: Tecnativa, Odoo Community Association (OCA)
Author-email: support@odoo-community.org
Classifier: Programming Language :: Python
Classifier: Framework :: Odoo
Classifier: Framework :: Odoo :: 17.0
Classifier: License :: OSI Approved :: GNU Affero General Public License v3
Classifier: Development Status :: 4 - Beta
